README.rst
setup.py
ahab/__init__.py
ahab/__main__.py
ahab/logger.py
ahab.egg-info/PKG-INFO
ahab.egg-info/SOURCES.txt
ahab.egg-info/dependency_links.txt
ahab.egg-info/entry_points.txt
ahab.egg-info/requires.txt
ahab.egg-info/top_level.txt
ahab/version/VERSION
ahab/version/__init__.py