Metadata-Version: 1.1
Name: ahab
Version: 20160206
Summary: Ahab: on which to hang your Docker hooks
Home-page: https://github.com/instacart/ahab
Author: Instacart
Author-email: open-source@instacart.com
License: UNKNOWN
Platform: UNKNOWN
Classifier: Environment :: Console
Classifier: Intended Audience :: Developers
Classifier: License :: OSI Approved :: ISC License (ISCL)
Classifier: Operating System :: Unix
Classifier: Operating System :: POSIX
Classifier: Programming Language :: Python
Classifier: Topic :: System
Classifier: Topic :: System :: Systems Administration
Classifier: Topic :: Software Development
Classifier: Development Status :: 4 - Beta
